facebook_publisher/__init__.py
facebook_publisher/client.py
facebook_publisher/exceptions.py
facebook_publisher/groups.py
facebook_publisher/login.py
facebook_publisher/posting.py
facebook_publisher/session.py
facebook_publisher/browser/__init__.py
facebook_publisher/browser/manager.py
facebook_publisher/utils/__init__.py
facebook_publisher/utils/log.py
facebook_publisher/utils/retry.py
facebook_publisher-0.1.1.dist-info/licenses/LICENSE
facebook_publisher-0.1.1.dist-info/METADATA
facebook_publisher-0.1.1.dist-info/WHEEL
facebook_publisher-0.1.1.dist-info/top_level.txt
facebook_publisher-0.1.1.dist-info/RECORD
