Metadata-Version: 2.4
Name: facebook-publisher
Version: 0.1.1
Summary: SDK para publicar en grupos de Facebook con Playwright
Author-email: espinosalastresr <espinosalastresr@gmail.com>
License: Copyright (c) 2025 Raydiel Espinosa
Requires-Python: >=3.10
License-File: LICENSE
Requires-Dist: playwright>=1.40
Dynamic: license-file
